odc/apps/dc_tools/__init__.py
odc/apps/dc_tools/_docs.py
odc/apps/dc_tools/_stac.py
odc/apps/dc_tools/_version.py
odc/apps/dc_tools/add_update_products.py
odc/apps/dc_tools/azure_to_dc.py
odc/apps/dc_tools/azure_to_tar.py
odc/apps/dc_tools/cop_dem_to_dc.py
odc/apps/dc_tools/esa_worldcover_to_dc.py
odc/apps/dc_tools/export_md.py
odc/apps/dc_tools/fs_to_dc.py
odc/apps/dc_tools/gs_to_tar.py
odc/apps/dc_tools/index_from_tar.py
odc/apps/dc_tools/redrive_to_queue.py
odc/apps/dc_tools/s3_find.py
odc/apps/dc_tools/s3_inventory.py
odc/apps/dc_tools/s3_to_dc.py
odc/apps/dc_tools/s3_to_tar.py
odc/apps/dc_tools/sqs_to_dc.py
odc/apps/dc_tools/stac_api_to_dc.py
odc/apps/dc_tools/thredds_to_dc.py
odc/apps/dc_tools/thredds_to_tar.py
odc/apps/dc_tools/utils.py
odc_apps_dc_tools-1.9.7.dist-info/licenses/LICENSE
odc_apps_dc_tools-1.9.7.dist-info/METADATA
odc_apps_dc_tools-1.9.7.dist-info/WHEEL
odc_apps_dc_tools-1.9.7.dist-info/entry_points.txt
odc_apps_dc_tools-1.9.7.dist-info/top_level.txt
odc_apps_dc_tools-1.9.7.dist-info/RECORD
