Metadata-Version: 2.4
Name: odc-apps-dc-tools
Version: 1.9.7
Summary: CLI utils for working with a datacube index
Author-email: Open Data Cube <earth.observation@ga.gov.au>
License-Expression: Apache-2.0
Project-URL: Homepage, https://github.com/opendatacube/odc-tools/
Requires-Python: >=3.10
License-File: LICENSE
Requires-Dist: click<8.3
Requires-Dist: datacube<1.10.0,>=1.9.12
Requires-Dist: datadog
Requires-Dist: fsspec
Requires-Dist: odc-cloud[ASYNC]>=0.2.3
Requires-Dist: odc-geo
Requires-Dist: odc_io
Requires-Dist: pystac-client>=0.2.0
Requires-Dist: pystac<2,>=1.0.0
Requires-Dist: pyyaml
Requires-Dist: rio-stac
Requires-Dist: toolz
Provides-Extra: tests
Requires-Dist: deepdiff; extra == "tests"
Requires-Dist: docker; extra == "tests"
Requires-Dist: flask; extra == "tests"
Requires-Dist: flask_cors; extra == "tests"
Requires-Dist: moto; extra == "tests"
Requires-Dist: odc-apps-dc-tools[azure,gcp,thredds]; extra == "tests"
Requires-Dist: psycopg2; extra == "tests"
Requires-Dist: pytest; extra == "tests"
Requires-Dist: pytest-cov; extra == "tests"
Requires-Dist: pytest_httpserver; extra == "tests"
Requires-Dist: pytest-timeout; extra == "tests"
Provides-Extra: azure
Requires-Dist: odc-cloud[AZURE]; extra == "azure"
Provides-Extra: gcp
Requires-Dist: google-cloud-storage; extra == "gcp"
Provides-Extra: thredds
Requires-Dist: odc-cloud[THREDDS]; extra == "thredds"
Dynamic: license-file
